jsonvalidator/__init__.py
jsonvalidator/cli.py
jsonvalidator_cli-0.1.0.dist-info/licenses/LICENSE
tests/__init__.py
tests/test_cli.py
jsonvalidator_cli-0.1.0.dist-info/METADATA
jsonvalidator_cli-0.1.0.dist-info/WHEEL
jsonvalidator_cli-0.1.0.dist-info/entry_points.txt
jsonvalidator_cli-0.1.0.dist-info/top_level.txt
jsonvalidator_cli-0.1.0.dist-info/RECORD
