Metadata-Version: 2.4
Name: jsonvalidator-cli
Version: 0.1.0
Summary: A simple CLI tool to validate JSON files
Home-page: https://github.com/bijesh-bits/jsonvalidator
Author: Bijesh
Author-email: Bijesh <bijesh@example.com>
License: MIT
Project-URL: Homepage, https://github.com/bijesh-bits/jsonvalidator
Project-URL: Documentation, https://github.com/bijesh-bits/jsonvalidator#readme
Project-URL: Repository, https://github.com/bijesh-bits/jsonvalidator
Project-URL: Bug Tracker, https://github.com/bijesh-bits/jsonvalidator/issues
Keywords: json,validator,cli,schema,jsonschema
Classifier: Development Status :: 4 - Beta
Classifier: Intended Audience :: Developers
Classifier: Topic :: Software Development :: Testing
Classifier: License :: OSI Approved :: MIT License
Classifier: Programming Language :: Python :: 3
Classifier: Programming Language :: Python :: 3.8
Classifier: Programming Language :: Python :: 3.9
Classifier: Programming Language :: Python :: 3.10
Classifier: Programming Language :: Python :: 3.11
Classifier: Programming Language :: Python :: 3.12
Requires-Python: >=3.8
License-File: LICENSE
Requires-Dist: jsonschema>=4.0.0
Provides-Extra: dev
Requires-Dist: pytest>=7.0.0; extra == "dev"
Requires-Dist: pytest-cov>=4.0.0; extra == "dev"
Requires-Dist: flake8>=6.0.0; extra == "dev"
Dynamic: author
Dynamic: home-page
Dynamic: license-file
Dynamic: requires-python
